pygwarts/__init__.py
pygwarts/filch/__init__.py
pygwarts/filch/marauders_map.py
pygwarts/filch/apppuf/__init__.py
pygwarts/filch/apppuf/snmp.py
pygwarts/filch/linkindor/__init__.py
pygwarts/filch/linkindor/arp.py
pygwarts/filch/nettherin/__init__.py
pygwarts/filch/nettherin/icmp.py
pygwarts/filch/transportclaw/__init__.py
pygwarts/filch/transportclaw/scanning.py
pygwarts/hagrid/__init__.py
pygwarts/hagrid/sprouts.py
pygwarts/hagrid/thrivables.py
pygwarts/hagrid/walks.py
pygwarts/hagrid/bloom/__init__.py
pygwarts/hagrid/bloom/leafs.py
pygwarts/hagrid/bloom/twigs.py
pygwarts/hagrid/bloom/weeds.py
pygwarts/hagrid/cultivation/__init__.py
pygwarts/hagrid/cultivation/registering.py
pygwarts/hagrid/cultivation/sifting.py
pygwarts/hagrid/planting/__init__.py
pygwarts/hagrid/planting/leafs.py
pygwarts/hagrid/planting/peeks.py
pygwarts/hagrid/planting/peels.py
pygwarts/hagrid/planting/twigs.py
pygwarts/hagrid/planting/weeds.py
pygwarts/hedwig/__init__.py
pygwarts/hedwig/mail/__init__.py
pygwarts/hedwig/mail/utils.py
pygwarts/hedwig/mail/builder/__init__.py
pygwarts/hedwig/mail/builder/client.py
pygwarts/hedwig/mail/builder/smtp.py
pygwarts/hedwig/mail/letter/__init__.py
pygwarts/hedwig/mail/letter/fields.py
pygwarts/irma/__init__.py
pygwarts/irma/access/__init__.py
pygwarts/irma/access/annex.py
pygwarts/irma/access/utils.py
pygwarts/irma/access/volume.py
pygwarts/irma/access/bookmarks/__init__.py
pygwarts/irma/access/bookmarks/counters.py
pygwarts/irma/access/bookmarks/viewers.py
pygwarts/irma/access/handlers/__init__.py
pygwarts/irma/access/handlers/counters.py
pygwarts/irma/access/handlers/parsers.py
pygwarts/irma/access/inducers/__init__.py
pygwarts/irma/access/inducers/case.py
pygwarts/irma/access/inducers/counters.py
pygwarts/irma/access/inducers/filters.py
pygwarts/irma/access/inducers/recap.py
pygwarts/irma/contrib/__init__.py
pygwarts/irma/contrib/intercept.py
pygwarts/irma/shelve/__init__.py
pygwarts/irma/shelve/casing.py
pygwarts/magical/__init__.py
pygwarts-1.5.1.4.dist-info/METADATA
pygwarts-1.5.1.4.dist-info/WHEEL
pygwarts-1.5.1.4.dist-info/top_level.txt
pygwarts-1.5.1.4.dist-info/RECORD
