Metadata-Version: 2.1
Name: pygwarts
Version: 1.5.1.4
Summary: Python multitool library
Home-page: https://github.com/longdeer/pygwarts
Author: lngd
Author-email: lngdeer@gmail.com
License: GPL-3.0 license
Platform: UNKNOWN
Requires-Python: >=3.10
